tinyflow/__init__.py
tinyflow/_compat.py
tinyflow/_testing.py
tinyflow/exceptions.py
tinyflow/ops.py
tinyflow/pipeline.py
tinyflow/tools.py
tinyflow-0.1.dist-info/DESCRIPTION.rst
tinyflow-0.1.dist-info/METADATA
tinyflow-0.1.dist-info/RECORD
tinyflow-0.1.dist-info/WHEEL
tinyflow-0.1.dist-info/metadata.json
tinyflow-0.1.dist-info/top_level.txt
tinyflow-0.1.dist-info/zip-safe
