Metadata-Version: 2.0
Name: tinyflow
Version: 0.1
Summary: Experimental in-memory data flow pipelines.
Home-page: https://github.com/geowurster/tinyflow
Author: Kevin Wurster
Author-email: wursterk@gmail.com
License: New BSD
Keywords: experimental memory data flow
Platform: UNKNOWN
Classifier: Topic :: Utilities
Classifier: Intended Audience :: Developers
Classifier: Development Status :: 3 - Alpha
Classifier: License :: OSI Approved :: BSD License
Classifier: Topic :: Text Processing
Classifier: Topic :: Software Development :: Libraries
Classifier: Programming Language :: Python :: 2
Classifier: Programming Language :: Python :: 3
Classifier: Programming Language :: Python :: Implementation :: PyPy
Provides-Extra: all
Requires-Dist: coveralls; extra == 'all'
Requires-Dist: pytest (>=3); extra == 'all'
Requires-Dist: pytest-cov; extra == 'all'
Provides-Extra: dev
Requires-Dist: coveralls; extra == 'dev'
Requires-Dist: pytest (>=3); extra == 'dev'
Requires-Dist: pytest-cov; extra == 'dev'
